corerec/12datasets.py
corerec/Tmodel.py
corerec/__init__.py
corerec/async_ddp.py
corerec/base_recommender.py
corerec/common_import.py
corerec/core_rec.py
corerec/hyper_train.py
corerec/metrics.py
corerec/models.py
corerec/predict.py
corerec/timecapsule.py
corerec/train.py
corerec/vish_graphs.py
corerec/visualization.py
corerec/cf_engine/__init__.py
corerec/cr_boosters/__init__.py
corerec/cr_boosters/_functional.py
corerec/cr_boosters/adadelta.py
corerec/cr_boosters/adagrad.py
corerec/cr_boosters/adam.py
corerec/cr_boosters/adamax.py
corerec/cr_boosters/asgd.py
corerec/cr_boosters/lbfgs.py
corerec/cr_boosters/lr_scheduler.py
corerec/cr_boosters/nadam.py
corerec/cr_boosters/optimizer.py
corerec/cr_boosters/radam.py
corerec/cr_boosters/rmsprop.py
corerec/cr_boosters/sgd.py
corerec/cr_boosters/sparse_adam.py
corerec/cr_boosters/swa_utils.py
corerec/cr_boosters/test_adam.py
corerec/cr_boosters/_multi_tensor/__init__.py
corerec/cr_boosters/_multi_tensor/__init__.pyi
corerec/cr_pkg/__init__.py
corerec/cr_pkg/gat_conv.py
corerec/cr_pkg/gat_conv_test.py
corerec/cr_pkg/gcn_conv.py
corerec/cr_pkg/gcn_conv_test.py
corerec/cr_pkg/han_conv.py
corerec/cr_pkg/han_conv_test.py
corerec/cr_pkg/sage_conv.py
corerec/cr_pkg/sage_conv_test.py
corerec/cr_utility/__init__.py
corerec/cr_utility/dataloader.py
corerec/cr_utility/dataset.py
corerec/engines/__init__.py
corerec/engines/contentFilterEngine/__init__.py
corerec/engines/contentFilterEngine/base_recommender.py
corerec/engines/contentFilterEngine/cr_contentFilterFactory.py
corerec/engines/contentFilterEngine/tfidf_recommender.py
corerec/engines/contentFilterEngine/context_personalization/__init__.py
corerec/engines/contentFilterEngine/context_personalization/context_aware.py
corerec/engines/contentFilterEngine/context_personalization/item_profiling.py
corerec/engines/contentFilterEngine/context_personalization/user_profiling.py
corerec/engines/contentFilterEngine/embedding_representation_learning/__init__.py
corerec-0.4.1.9.dist-info/LICENSE.txt
corerec-0.4.1.9.dist-info/METADATA
corerec-0.4.1.9.dist-info/WHEEL
corerec-0.4.1.9.dist-info/top_level.txt
corerec-0.4.1.9.dist-info/RECORD
